{
  "questions": [
    {
      "question": "2019 yapımı \"Joker\" filmindeki başrol performansıyla En İyi Erkek Oyuncu Oscar'ını kazanan aktör kimdir?",
      "options": [
        "Christian Bale",
        "Robert Pattinson",
        "Joaquin Phoenix",
        "Heath Ledger",
        "Ben Affleck"
      ],
      "correct": 2
    },
    {
      "question": "Güney Koreli global fenomen K-Pop grubu BTS'in üye sayısı kaçtır?",
      "options": [
        "5",
        "6",
        "7",
        "8",
        "9"
      ],
      "correct": 2
    },
    {
      "question": "Rihanna, 2015 Met Gala'da \"China: Through the Looking Glass\" temasına uygun giydiği, Çinli tasarımcı Guo Pei imzalı ikonik sarı peleriniyle büyük yankı uyandırmıştı. Bu pelerinin kuyruğunun uzunluğu nedeniyle sosyal medyada en çok hangi yiyeceğe benzetilmiştir?",
      "options": [
        "Omlet",
        "Pizza",
        "Mantı",
        "Sosisli",
        "Krep"
      ],
      "correct": 0
    },
    {
      "question": "Erkekler tenis tarihinde, Roland Garros'ta (Fransa Açık) en çok şampiyonluk kazanan ve \"Toprak Kortun Kralı\" lakabıyla bilinen efsanevi tenisçi kimdir?",
      "options": [
        "Roger Federer",
        "Novak Djokovic",
        "Andy Murray",
        "Rafael Nadal",
        "Pete Sampras"
      ],
      "correct": 3
    },
    {
      "question": "Netflix'in dünya çapında popüler İspanyol dizisi \"La Casa de Papel\"de, ekibin soygun planlarını yapan ve zekasıyla öne çıkan lider karakterin lakabı nedir?",
      "options": [
        "Berlin",
        "Profesör",
        "Tokyo",
        "Denver",
        "Rio"
      ],
      "correct": 1
    }
  ]
}